odoo/addons/mail_activity_future_counter/README.rst
odoo/addons/mail_activity_future_counter/__init__.py
odoo/addons/mail_activity_future_counter/__manifest__.py
odoo/addons/mail_activity_future_counter/i18n/it.po
odoo/addons/mail_activity_future_counter/i18n/mail_activity_future_counter.pot
odoo/addons/mail_activity_future_counter/readme/DESCRIPTION.md
odoo/addons/mail_activity_future_counter/static/description/icon.png
odoo/addons/mail_activity_future_counter/static/description/index.html
odoo/addons/mail_activity_future_counter/static/src/activity_menu_patch.esm.js
odoo/addons/mail_activity_future_counter/static/src/activity_menu_patch.scss
odoo/addons/mail_activity_future_counter/static/src/activity_menu_patch.xml
odoo_addon_mail_activity_future_counter-17.0.1.0.0.3.dist-info/METADATA
odoo_addon_mail_activity_future_counter-17.0.1.0.0.3.dist-info/WHEEL
odoo_addon_mail_activity_future_counter-17.0.1.0.0.3.dist-info/top_level.txt
odoo_addon_mail_activity_future_counter-17.0.1.0.0.3.dist-info/RECORD
